azure/mgmt/impactreporting/__init__.py
azure/mgmt/impactreporting/_client.py
azure/mgmt/impactreporting/_configuration.py
azure/mgmt/impactreporting/_model_base.py
azure/mgmt/impactreporting/_patch.py
azure/mgmt/impactreporting/_serialization.py
azure/mgmt/impactreporting/_version.py
azure/mgmt/impactreporting/py.typed
azure/mgmt/impactreporting/aio/__init__.py
azure/mgmt/impactreporting/aio/_client.py
azure/mgmt/impactreporting/aio/_configuration.py
azure/mgmt/impactreporting/aio/_patch.py
azure/mgmt/impactreporting/aio/operations/__init__.py
azure/mgmt/impactreporting/aio/operations/_operations.py
azure/mgmt/impactreporting/aio/operations/_patch.py
azure/mgmt/impactreporting/models/__init__.py
azure/mgmt/impactreporting/models/_enums.py
azure/mgmt/impactreporting/models/_models.py
azure/mgmt/impactreporting/models/_patch.py
azure/mgmt/impactreporting/operations/__init__.py
azure/mgmt/impactreporting/operations/_operations.py
azure/mgmt/impactreporting/operations/_patch.py
azure_mgmt_impactreporting-1.0.0b1.dist-info/LICENSE
azure_mgmt_impactreporting-1.0.0b1.dist-info/METADATA
azure_mgmt_impactreporting-1.0.0b1.dist-info/WHEEL
azure_mgmt_impactreporting-1.0.0b1.dist-info/top_level.txt
azure_mgmt_impactreporting-1.0.0b1.dist-info/RECORD
